pydantic_extra_types/__init__.py
pydantic_extra_types-0.0.1.dist-info/METADATA
pydantic_extra_types-0.0.1.dist-info/WHEEL
pydantic_extra_types-0.0.1.dist-info/licenses/LICENSE
pydantic_extra_types-0.0.1.dist-info/RECORD
